behave4git/__all_steps__.py
behave4git/__version__.py
behave4git/git_steps.py
behave4git/utils.py
behave4git-0.4.0.dist-info/LICENSE
behave4git-0.4.0.dist-info/WHEEL
behave4git-0.4.0.dist-info/METADATA
behave4git-0.4.0.dist-info/RECORD
