Metadata-Version: 2.1
Name: behave4git
Version: 0.4.0
Summary: This project provides an extension (testing domain) of Behave to use Git and GitLab (and GitHub in the near future).
Home-page: https://github.com/opinionated-digital-center/behave4git
License: MIT
Keywords: behave4git,behave4cmd,behave,bdd
Author: Emmanuel Sciara
Author-email: emmanuel.sciara@gmail.com
Requires-Python: >=3.6.1,<4.0.0
Classifier: Development Status :: 4 - Beta
Classifier: Environment :: Console
Classifier: Intended Audience :: Developers
Classifier: License :: OSI Approved :: MIT License
Classifier: Operating System :: OS Independent
Classifier: Programming Language :: Python :: 3
Classifier: Programming Language :: Python :: 3.10
Classifier: Programming Language :: Python :: 3.6
Classifier: Programming Language :: Python :: 3.7
Classifier: Programming Language :: Python :: 3.8
Classifier: Programming Language :: Python :: 3.9
Classifier: Programming Language :: Python :: Implementation :: CPython
Classifier: Programming Language :: Python :: Implementation :: Jython
Classifier: Programming Language :: Python :: Implementation :: PyPy
Classifier: Topic :: Software Development :: Testing
Provides-Extra: bdd
Provides-Extra: docs
Provides-Extra: format
Provides-Extra: lint
Provides-Extra: repl
Provides-Extra: test
Provides-Extra: type
Requires-Dist: PyHamcrest (>=2.0.2,<3.0.0)
Requires-Dist: behave (>=1.2.6,<2.0.0)
Requires-Dist: behave4cli (>=1.1,<2.0)
Requires-Dist: black; extra == "format"
Requires-Dist: bpython (>=0.18,<0.19); extra == "repl"
Requires-Dist: flake8 (>=4.0,<5.0); extra == "lint"
Requires-Dist: flake8-bugbear (>=21.0.0,<22.0.0); extra == "lint"
Requires-Dist: gitpython (>=3.1.1,<4.0.0)
Requires-Dist: isort (>=5,<6); extra == "format"
Requires-Dist: mock (>=4.0.2,<5.0.0); extra == "test"
Requires-Dist: mypy (>=0.740.0,<0.741.0); extra == "bdd" or extra == "type"
Requires-Dist: pydocstyle (>=3.0,<4.0); extra == "lint"
Requires-Dist: pylint (>=2.3,<3.0); extra == "lint"
Requires-Dist: pytest (>=5.1,<6.0); extra == "test"
Requires-Dist: pytest-asyncio (>=0.14.0,<0.15.0); extra == "test"
Requires-Dist: pytest-cov (>=2.8.1,<3.0.0); extra == "test"
Requires-Dist: pytest-html (>=2.0.1,<3.0.0); extra == "test"
Requires-Dist: pytest-mock (>=1.13.0,<2.0.0); extra == "test"
Requires-Dist: seed-isort-config (>=2.2,<3.0); extra == "format"
Requires-Dist: sphinx (>=2.3.0,<3.0.0); extra == "docs"
Requires-Dist: sphinx-autobuild (>=0.7.1,<0.8.0); extra == "docs"
Requires-Dist: sphinx-autodoc-typehints (>=1.10.3,<2.0.0); extra == "docs"
Requires-Dist: sphinx_rtd_theme (>=0.5.0,<0.6.0); extra == "docs"
Requires-Dist: yapf (>=0.30.0,<0.31.0); extra == "lint"
